stratestic/backtesting/__init__.py
stratestic/backtesting/_mixin.py
stratestic/backtesting/combining/__init__.py
stratestic/backtesting/combining/_combining.py
stratestic/backtesting/helpers/__init__.py
stratestic/backtesting/helpers/evaluation/__init__.py
stratestic/backtesting/helpers/evaluation/_constants.py
stratestic/backtesting/helpers/evaluation/_results.py
stratestic/backtesting/helpers/evaluation/metrics.py
stratestic/backtesting/helpers/margin/__init__.py
stratestic/backtesting/helpers/margin/_margin.py
stratestic/backtesting/helpers/plotting/__init__.py
stratestic/backtesting/helpers/plotting/_plotting.py
stratestic/backtesting/helpers/trade.py
stratestic/backtesting/iterative/__init__.py
stratestic/backtesting/iterative/_iterative.py
stratestic/backtesting/optimization/__init__.py
stratestic/backtesting/optimization/_optimization.py
stratestic/backtesting/vectorized/__init__.py
stratestic/backtesting/vectorized/_vectorized.py
stratestic/strategies/__init__.py
stratestic/strategies/_mixin.py
stratestic/strategies/machine_learning/__init__.py
stratestic/strategies/machine_learning/helpers/__init__.py
stratestic/strategies/machine_learning/helpers/_defaults.py
stratestic/strategies/machine_learning/helpers/_evaluation.py
stratestic/strategies/machine_learning/helpers/_feature_engineering.py
stratestic/strategies/machine_learning/helpers/_helpers.py
stratestic/strategies/machine_learning/helpers/_pipeline_custom_classes.py
stratestic/strategies/machine_learning/helpers/_training.py
stratestic/strategies/machine_learning/machine_learning.py
stratestic/strategies/machine_learning/models/__init__.py
stratestic/strategies/mean_reversion/__init__.py
stratestic/strategies/mean_reversion/bollinger_bands.py
stratestic/strategies/moving_average/__init__.py
stratestic/strategies/moving_average/ma.py
stratestic/strategies/moving_average/ma_crossover.py
stratestic/strategies/moving_average/macd.py
stratestic/strategies/properties.py
stratestic-1.6.1.dist-info/METADATA
stratestic-1.6.1.dist-info/WHEEL
stratestic-1.6.1.dist-info/RECORD
