Metadata-Version: 2.1
Name: stratestic
Version: 1.6.1
Summary: Library for testing and analysing trading strategies.
Home-page: https://github.com/diogomatoschaves/stratestic
License: MIT
Keywords: backtesting,trading,algotrading,trading-strategies,algorithmic-trading
Author: Diogo Matos Chaves
Author-email: diogo_chaves@hotmail.com
Requires-Python: >=3.8,<3.11
Classifier: License :: OSI Approved :: MIT License
Classifier: Programming Language :: Python :: 3
Classifier: Programming Language :: Python :: 3.8
Classifier: Programming Language :: Python :: 3.9
Classifier: Programming Language :: Python :: 3.10
Requires-Dist: dill (>=0.3.8,<0.4.0)
Requires-Dist: geneal (>=0.7.0,<0.8.0)
Requires-Dist: humanfriendly (>=10.0,<11.0)
Requires-Dist: matplotlib (>=3.4.1,<4.0.0)
Requires-Dist: numba (==0.56.2)
Requires-Dist: numpy (>=1.20.2,<2.0.0)
Requires-Dist: pandas (>=1.2.3,<2.0.0)
Requires-Dist: plotly (>=5.14.1,<6.0.0)
Requires-Dist: progressbar2 (>=4.2.0,<5.0.0)
Requires-Dist: python-dotenv (>=0.17.0,<0.18.0)
Requires-Dist: scikit-learn (>=1.0.0,<2.0.0)
Requires-Dist: scipy (>=1.6.2,<2.0.0)
Requires-Dist: seaborn (>=0.11.1,<0.12.0)
Requires-Dist: ta (>=0.7.0,<0.8.0)
Requires-Dist: tzdata (==2022.7)
Project-URL: Repository, https://github.com/diogomatoschaves/stratestic
